sphinx_gallery/__init__.py
sphinx_gallery/backreferences.py
sphinx_gallery/block_parser.py
sphinx_gallery/directives.py
sphinx_gallery/docs_resolv.py
sphinx_gallery/downloads.py
sphinx_gallery/gen_gallery.py
sphinx_gallery/gen_rst.py
sphinx_gallery/interactive_example.py
sphinx_gallery/load_style.py
sphinx_gallery/notebook.py
sphinx_gallery/py_source_parser.py
sphinx_gallery/recommender.py
sphinx_gallery/scrapers.py
sphinx_gallery/sorting.py
sphinx_gallery/utils.py
sphinx_gallery/_dummy/__init__.py
sphinx_gallery/_dummy/nested.py
sphinx_gallery/_static/binder_badge_logo.svg
sphinx_gallery/_static/broken_example.png
sphinx_gallery/_static/jupyterlite_badge_logo.svg
sphinx_gallery/_static/no_image.png
sphinx_gallery/_static/sg_gallery-binder.css
sphinx_gallery/_static/sg_gallery-dataframe.css
sphinx_gallery/_static/sg_gallery-rendered-html.css
sphinx_gallery/_static/sg_gallery.css
sphinx_gallery/components/sg_download_links.html
sphinx_gallery/components/sg_launcher_links.html
sphinx_gallery/tests/__init__.py
sphinx_gallery/tests/conftest.py
sphinx_gallery/tests/reference_parse.txt
sphinx_gallery/tests/test_backreferences.py
sphinx_gallery/tests/test_block_parser.py
sphinx_gallery/tests/test_docs_resolv.py
sphinx_gallery/tests/test_full.py
sphinx_gallery/tests/test_full_noexec.py
sphinx_gallery/tests/test_gen_gallery.py
sphinx_gallery/tests/test_gen_rst.py
sphinx_gallery/tests/test_interactive_example.py
sphinx_gallery/tests/test_load_style.py
sphinx_gallery/tests/test_notebook.py
sphinx_gallery/tests/test_py_source_parser.py
sphinx_gallery/tests/test_recommender.py
sphinx_gallery/tests/test_scrapers.py
sphinx_gallery/tests/test_sorting.py
sphinx_gallery/tests/testconfs/index.rst
sphinx_gallery/tests/testconfs/src/GALLERY_HEADER.rst
sphinx_gallery/tests/testconfs/src/plot_1.py
sphinx_gallery/tests/testconfs/src/plot_2.py
sphinx_gallery/tests/testconfs/src/plot_3.py
sphinx_gallery/tests/tinybuild/utils.py
sphinx_gallery/tests/tinybuild/doc/Makefile
sphinx_gallery-0.18.0.dist-info/LICENSE
sphinx_gallery-0.18.0.dist-info/METADATA
sphinx_gallery-0.18.0.dist-info/WHEEL
sphinx_gallery-0.18.0.dist-info/entry_points.txt
sphinx_gallery-0.18.0.dist-info/top_level.txt
sphinx_gallery-0.18.0.dist-info/RECORD
