Metadata-Version: 2.1
Name: sphinx-gallery
Version: 0.18.0
Summary: A Sphinx extension that builds an HTML gallery of examples from any set of Python scripts.
Author-email: Óscar Nájera <najera.oscar@gmail.com>
License: 3-clause BSD
Project-URL: Documentation, https://sphinx-gallery.github.io
Project-URL: Source, https://github.com/sphinx-gallery/sphinx-gallery
Classifier: Development Status :: 4 - Beta
Classifier: Framework :: Sphinx :: Extension
Classifier: Intended Audience :: Developers
Classifier: Programming Language :: Python
Classifier: Programming Language :: Python :: 3 :: Only
Classifier: Programming Language :: Python :: 3.8
Classifier: Programming Language :: Python :: 3.9
Classifier: Programming Language :: Python :: 3.10
Classifier: Programming Language :: Python :: 3.11
Classifier: Programming Language :: Python :: 3.12
Requires-Python: >=3.8
License-File: LICENSE
Requires-Dist: pillow
Requires-Dist: sphinx>=5
Provides-Extra: animations
Requires-Dist: sphinxcontrib-video; extra == "animations"
Provides-Extra: dev
Requires-Dist: absl-py; extra == "dev"
Requires-Dist: graphviz; extra == "dev"
Requires-Dist: intersphinx-registry; extra == "dev"
Requires-Dist: ipython; extra == "dev"
Requires-Dist: joblib; extra == "dev"
Requires-Dist: jupyterlite-sphinx; extra == "dev"
Requires-Dist: lxml; extra == "dev"
Requires-Dist: matplotlib; extra == "dev"
Requires-Dist: numpy; extra == "dev"
Requires-Dist: packaging; extra == "dev"
Requires-Dist: plotly; extra == "dev"
Requires-Dist: pydata-sphinx-theme; extra == "dev"
Requires-Dist: pytest; extra == "dev"
Requires-Dist: pytest-coverage; extra == "dev"
Requires-Dist: seaborn; extra == "dev"
Requires-Dist: sphinxcontrib-video; extra == "dev"
Requires-Dist: statsmodels; extra == "dev"
Provides-Extra: jupyterlite
Requires-Dist: jupyterlite-sphinx; extra == "jupyterlite"
Provides-Extra: parallel
Requires-Dist: joblib; extra == "parallel"
Provides-Extra: recommender
Requires-Dist: numpy; extra == "recommender"
Provides-Extra: show-api-usage
Requires-Dist: graphviz; extra == "show-api-usage"
Provides-Extra: show-memory
Requires-Dist: memory-profiler; extra == "show-memory"
